MANIFEST.in
README.rst
requirements.txt
setup.py
py_tvd.egg-info/PKG-INFO
py_tvd.egg-info/SOURCES.txt
py_tvd.egg-info/dependency_links.txt
py_tvd.egg-info/requires.txt
py_tvd.egg-info/top_level.txt
tvd/__init__.py
tvd/core.py
tvd/version.py