Metadata-Version: 1.0
Name: py-tvd
Version: 1.0
Summary: A total variation denoising implementation in python.
Home-page: https://github.com/PNProductions/py-tvd
Author: Piero Dotti, Paolo Guglielmini
Author-email: pnproductions.dev@gmail.com
License: UNKNOWN
Platform: UNKNOWN
